SpringDataJdbc105ReleaseZhongwenWendang/README.md
SpringDataJdbc105ReleaseZhongwenWendang/__init__.py
SpringDataJdbc105ReleaseZhongwenWendang/__main__.py
SpringDataJdbc105ReleaseZhongwenWendang/file.epub
SpringDataJdbc105ReleaseZhongwenWendang/index.html
SpringDataJdbc105ReleaseZhongwenWendang/css/__init__.py
SpringDataJdbc105ReleaseZhongwenWendang/css/annotations.css
SpringDataJdbc105ReleaseZhongwenWendang/css/main.css
SpringDataJdbc105ReleaseZhongwenWendang/css/normalize.css
SpringDataJdbc105ReleaseZhongwenWendang/css/popup.css
SpringDataJdbc105ReleaseZhongwenWendang/font/__init__.py
SpringDataJdbc105ReleaseZhongwenWendang/font/fontello.eot
SpringDataJdbc105ReleaseZhongwenWendang/font/fontello.svg
SpringDataJdbc105ReleaseZhongwenWendang/font/fontello.ttf
SpringDataJdbc105ReleaseZhongwenWendang/font/fontello.woff
SpringDataJdbc105ReleaseZhongwenWendang/img/__init__.py
SpringDataJdbc105ReleaseZhongwenWendang/img/annotator-glyph-sprite.png
SpringDataJdbc105ReleaseZhongwenWendang/img/annotator-icon-sprite.png
SpringDataJdbc105ReleaseZhongwenWendang/img/apple-touch-icon.png
SpringDataJdbc105ReleaseZhongwenWendang/img/cancelfullscreen.png
SpringDataJdbc105ReleaseZhongwenWendang/img/close.png
SpringDataJdbc105ReleaseZhongwenWendang/img/fullscreen.png
SpringDataJdbc105ReleaseZhongwenWendang/img/loader.gif
SpringDataJdbc105ReleaseZhongwenWendang/img/menu-icon.png
SpringDataJdbc105ReleaseZhongwenWendang/img/save.png
SpringDataJdbc105ReleaseZhongwenWendang/img/saved.png
SpringDataJdbc105ReleaseZhongwenWendang/img/settings-s.png
SpringDataJdbc105ReleaseZhongwenWendang/img/settings.png
SpringDataJdbc105ReleaseZhongwenWendang/img/star.png
SpringDataJdbc105ReleaseZhongwenWendang/js/__init__.py
SpringDataJdbc105ReleaseZhongwenWendang/js/epub.js
SpringDataJdbc105ReleaseZhongwenWendang/js/epub.min.js
SpringDataJdbc105ReleaseZhongwenWendang/js/epub.min.map
SpringDataJdbc105ReleaseZhongwenWendang/js/hooks.min.js
SpringDataJdbc105ReleaseZhongwenWendang/js/hooks.min.map
spring_data_jdbc_1_0_5_release_zhongwen_wendang-2024.3.5.0.dist-info/METADATA
spring_data_jdbc_1_0_5_release_zhongwen_wendang-2024.3.5.0.dist-info/WHEEL
spring_data_jdbc_1_0_5_release_zhongwen_wendang-2024.3.5.0.dist-info/entry_points.txt
spring_data_jdbc_1_0_5_release_zhongwen_wendang-2024.3.5.0.dist-info/top_level.txt
spring_data_jdbc_1_0_5_release_zhongwen_wendang-2024.3.5.0.dist-info/RECORD
